passagemath_combinat/__init__.py
passagemath_combinat-10.6.47.dist-info/DELVEWHEEL
passagemath_combinat-10.6.47.dist-info/METADATA
passagemath_combinat-10.6.47.dist-info/RECORD
passagemath_combinat-10.6.47.dist-info/top_level.txt
passagemath_combinat-10.6.47.dist-info/WHEEL
passagemath_combinat.libs/libgmp-10-6a8fe126122672a8aed2558e30454e74.dll
passagemath_combinat.libs/libsymmetrica-3-3a6565d79a3407b01bc24b37253dbf7c.dll
sage/all__sagemath_combinat.py
sage/algebras/affine_nil_temperley_lieb.py
sage/algebras/all.py
sage/algebras/all__sagemath_combinat.py
sage/algebras/askey_wilson.py
sage/algebras/associated_graded.py
sage/algebras/cellular_basis.py
sage/algebras/cluster_algebra.py
sage/algebras/down_up_algebra.py
sage/algebras/free_algebra.py
sage/algebras/free_algebra_element.py
sage/algebras/free_algebra_quotient.py
sage/algebras/free_algebra_quotient_element.py
sage/algebras/free_zinbiel_algebra.py
sage/algebras/hall_algebra.py
sage/algebras/iwahori_hecke_algebra.py
sage/algebras/jordan_algebra.py
sage/algebras/nil_coxeter_algebra.py
sage/algebras/quantum_clifford.py
sage/algebras/quantum_matrix_coordinate_algebra.py
sage/algebras/quantum_oscillator.py
sage/algebras/quaternion_algebra.py
sage/algebras/quaternion_algebra_element.py
sage/algebras/q_commuting_polynomials.py
sage/algebras/q_system.py
sage/algebras/rational_cherednik_algebra.py
sage/algebras/schur_algebra.py
sage/algebras/shuffle_algebra.py
sage/algebras/splitting_algebra.py
sage/algebras/tensor_algebra.py
sage/algebras/yangian.py
sage/algebras/yokonuma_hecke_algebra.py
sage/algebras/hecke_algebras/all.py
sage/algebras/hecke_algebras/ariki_koike_algebra.py
sage/algebras/hecke_algebras/ariki_koike_specht_modules.py
sage/algebras/hecke_algebras/cubic_hecke_algebra.py
sage/algebras/hecke_algebras/cubic_hecke_base_ring.py
sage/algebras/hecke_algebras/cubic_hecke_matrix_rep.py
sage/algebras/lie_conformal_algebras/abelian_lie_conformal_algebra.py
sage/algebras/lie_conformal_algebras/affine_lie_conformal_algebra.py
sage/algebras/lie_conformal_algebras/all.py
sage/algebras/lie_conformal_algebras/bosonic_ghosts_lie_conformal_algebra.py
sage/algebras/lie_conformal_algebras/examples.py
